{"BestOfferEnabled": true, "Description": "Immaculate left-handed bass guitar from a Kansas City Based Artist/Collector's Estate. 5 string. Original Stuart Spector case included.", "ItemID": "323586384418", "EndTime": "2018-12-12T15:30:53.000Z", "StartTime": "2018-12-07T03:04:15.000Z", "ViewItemURLForNaturalSearch": "https://www.ebay.com/itm/Left-Handed-Spector-DLX-2-Tone-Cherryburst-/323586384418", "ListingType": "Chinese", "Location": "Kansas City, Missouri", "PaymentMethods": ["PayPal"], "GalleryURL": "https://thumbs3.ebaystatic.com/pict/3235863844188080_1.jpg", "PictureURL": ["https://i.ebayimg.com/00/s/MTYwMFgxMjAw/z/xqYAAOSwsDZb92uI/$_12.JPG?set_id=880000500F", "https://i.ebayimg.com/00/s/MTYwMFgxMjAw/z/ApEAAOSwbbJb92uE/$_12.JPG?set_id=880000500F", "https://i.ebayimg.com/00/s/MTYwMFgxMjAw/z/95QAAOSwmE9b92uU/$_12.JPG?set_id=880000500F", "https://i.ebayimg.com/00/s/MTYwMFgxMjAw/z/Ox0AAOSwwtdb92uN/$_12.JPG?set_id=880000500F", "https://i.ebayimg.com/00/s/MTYwMFgxMjAw/z/ze8AAOSwAzxb92uR/$_12.JPG?set_id=880000500F"], "PostalCode": "64119", "PrimaryCategoryID": "33034", "PrimaryCategoryName": "Musical Instruments & Gear:Guitars & Basses:Electric Guitars", "Quantity": 1, "Seller": {"UserID": "floridagators1792", "FeedbackRatingStar": "Blue", "FeedbackScore": 87, "PositiveFeedbackPercent": 100.0}, "BidCount": 1, "ConvertedCurrentPrice": {"Value": 1000.0, "CurrencyID": "USD"}, "CurrentPrice": {"Value": 1000.0, "CurrencyID": "USD"}, "HighBidder": {"UserID": "m***c", "FeedbackPrivate": false, "FeedbackRatingStar": "Turquoise", "FeedbackScore": 219}, "ListingStatus": "Completed", "QuantitySold": 1, "ShipToLocations": ["US"], "Site": "US", "TimeLeft": "PT0S", "Title": "Left-Handed Spector DLX 2-Tone Cherryburst", "ItemSpecifics": {"NameValueList": [{"Name": "Brand", "Value": ["Spector"]}, {"Name": "Non-Domestic Product", "Value": ["Yes"]}, {"Name": "String Configuration", "Value": ["5 String"]}, {"Name": "Model", "Value": ["MB6077"]}, {"Name": "Right-/ Left-Handed", "Value": ["Left-Handed"]}, {"Name": "Bundle Description", "Value": ["Guitar and Case"]}, {"Name": "Country/Region of Manufacture", "Value": ["Czech Republic"]}]}, "HitCount": 19, "PrimaryCategoryIDPath": "619:3858:33034", "Country": "US", "ReturnPolicy": {"ReturnsAccepted": "ReturnsNotAccepted"}, "MinimumToBid": {"Value": 1025.0, "CurrencyID": "USD"}, "AutoPay": false, "PaymentAllowedSite": [], "IntegratedMerchantCreditCardEnabled": false, "HandlingTime": 3, "ConditionID": 3000, "ConditionDisplayName": "Used", "GlobalShipping": false, "QuantitySoldByPickupInStore": 0, "NewBestOffer": false}