{"BestOfferEnabled": false, "Description": "HELLO FRESH FROM AN ESTATE THIS VINTAGE ELECTRIC GUITAR FROM TAKAMINE IT IS A 6 STRING GX 100 AND IS IN NEAR PERFECT SHAPE COMES WITH HARD CASE, GOOD LUCK. SORRY FOR SHIPPING UPS IS HIGH AND DEPENDING ZIPCODE, SO IF IT IS CHEAPER, I WILL REFUND THE DIFFERENCE. THANK YOU.", "ItemID": "163357487066", "EndTime": "2018-11-13T04:28:02.000Z", "StartTime": "2018-11-06T04:28:02.000Z", "ViewItemURLForNaturalSearch": "https://www.ebay.com/itm/Vintage-1980s-Rare-TAKAMINE-Made-Japan-GX-100-BLACK-RED-Electric-Guitar-NR-/163357487066", "ListingType": "Chinese", "Location": "Niagara, Wisconsin", "PaymentMethods": ["PayPal"], "GalleryURL": "https://thumbs3.ebaystatic.com/pict/1633574870668080_1.jpg", "PictureURL": ["https://i.ebayimg.com/00/s/MTIwMFgxNTk5/z/N5AAAOSw~G9bzT1F/$_57.JPG?set_id=8800005007", "https://i.ebayimg.com/00/s/MTIwMFgxNTk5/z/3VMAAOSwhrFbzT1K/$_57.JPG?set_id=8800005007", "https://i.ebayimg.com/00/s/MTIwMFgxNTk5/z/e7wAAOSwqeVbzT1T/$_57.JPG?set_id=8800005007", "https://i.ebayimg.com/00/s/MTIwMFgxNTk5/z/X4kAAOSw~4hbzT1c/$_57.JPG?set_id=8800005007", "https://i.ebayimg.com/00/s/MTIwMFgxNTk5/z/C8gAAOSwGI9bzT1j/$_57.JPG?set_id=8800005007", "https://i.ebayimg.com/00/s/MTIwMFgxNTk5/z/s6oAAOSwhgtbzT1q/$_57.JPG?set_id=8800005007", "https://i.ebayimg.com/00/s/MTIwMFgxNTk5/z/fyIAAOSw86NbzT1z/$_57.JPG?set_id=8800005007", "https://i.ebayimg.com/00/s/MTIwMFgxNTk5/z/HqkAAOSwR~tbzT15/$_57.JPG?set_id=8800005007", "https://i.ebayimg.com/00/s/MTYwMFgxMjAw/z/IkUAAOSwXolb0fDh/$_12.JPG?set_id=880000500F", "https://i.ebayimg.com/00/s/MTYwMFgxMjAw/z/vgQAAOSwElxb0fER/$_12.JPG?set_id=880000500F", "https://i.ebayimg.com/00/s/MTYwMFgxMjAw/z/Un4AAOSwxxVb0fEe/$_12.JPG?set_id=880000500F", "https://i.ebayimg.com/00/s/MTYwMFgxMjAw/z/RGQAAOSwHb9b0gGZ/$_12.JPG?set_id=880000500F"], "PostalCode": "54151", "PrimaryCategoryID": "33034", "PrimaryCategoryName": "Musical Instruments & Gear:Guitars & Basses:Electric Guitars", "Quantity": 1, "Seller": {"UserID": "recycledantiques", "FeedbackRatingStar": "Red", "FeedbackScore": 3233, "PositiveFeedbackPercent": 100.0}, "BidCount": 2, "ConvertedCurrentPrice": {"Value": 260.0, "CurrencyID": "USD"}, "CurrentPrice": {"Value": 260.0, "CurrencyID": "USD"}, "HighBidder": {"UserID": ".***a", "FeedbackPrivate": false, "FeedbackRatingStar": "Turquoise", "FeedbackScore": 402}, "ListingStatus": "Completed", "QuantitySold": 1, "ShipToLocations": ["US", "CA", "GB", "DK", "RO", "SK", "BG", "CZ", "FI", "HU", "LV", "LT", "MT", "EE", "AU", "GR", "PT", "CY", "SI", "JP", "CN", "SE", "KR", "ID", "TW", "TH", "BE", "FR", "HK", "IE", "NL", "PL", "ES", "IT", "DE", "AT", "IL", "MX", "NZ", "SG", "CH", "NO", "SA", "UA", "AE", "QA", "KW", "BH", "HR", "MY", "CL", "CO", "CR", "PA", "TT", "GT", "HN", "JM", "AG", "AW", "BZ", "DM", "GD", "KN", "LC", "MS", "TC", "BB", "BD", "BM", "BN", "BO", "EG", "GF", "GG", "GI", "GP", "IS", "JE", "JO", "KH", "KY", "LI", "LK", "LU", "MC", "MO", "MQ", "MV", "NI", "OM", "PK", "PY", "RE"], "Site": "US", "TimeLeft": "PT0S", "Title": "Vintage 1980s Rare TAKAMINE Made in Japan GX-100 BLACK & RED Electric Guitar NR", "ItemSpecifics": {"NameValueList": [{"Name": "Brand", "Value": ["Takamine"]}, {"Name": "Model", "Value": ["Vintage G100"]}, {"Name": "Exact Year", "Value": ["1980"]}, {"Name": "Country/Region of Manufacture", "Value": ["Japan"]}, {"Name": "Body Color", "Value": ["Black"]}, {"Name": "MPN", "Value": ["Does Not Apply"]}]}, "HitCount": 306, "PrimaryCategoryIDPath": "619:3858:33034", "Storefront": {"StoreURL": "https://stores.ebay.com/id=1200067280", "StoreName": "recycledantiques"}, "Country": "US", "ReturnPolicy": {"Refund": "Money Back", "ReturnsWithin": "30 Days", "ReturnsAccepted": "Returns Accepted", "ShippingCostPaidBy": "Seller", "InternationalReturnsAccepted": "ReturnsNotAccepted"}, "MinimumToBid": {"Value": 265.0, "CurrencyID": "USD"}, "AutoPay": false, "PaymentAllowedSite": [], "IntegratedMerchantCreditCardEnabled": false, "HandlingTime": 3, "ConditionID": 3000, "ConditionDisplayName": "Used", "GlobalShipping": true, "ConditionDescription": "NEAR PERFECT NO CHIPS MISSING OUT OF THE CORNERS", "QuantitySoldByPickupInStore": 0, "NewBestOffer": false}