{"BestOfferEnabled": true, "Description": "Up for sale we have a used Fender Player Series Stratocaster HSS Tobacco Sunburst that comes with a hardshell tweed case. This item is in great condition, there are no visible scratches or marks and it sounds fantastic.This item features:Solid body made of Alder (gloss polyester finish)Maple neck (satin polyurethane finish)Fender 2-point \"Synchronized Tremolo\" floating vibrato bridge/tailpiece Alnico II bridge humbucker packs punch and output Alnico V single-coils 9.5\"-radius fingerboard with 22 medium-jumbo frets This item is being sold by Bang! Music, Inc. located in Stafford, Virginia where we have been family owned and operated since 1997.", "ItemID": "333010106076", "EndTime": "2019-01-12T16:26:41.000Z", "StartTime": "2019-01-11T21:13:18.000Z", "ViewItemURLForNaturalSearch": "https://www.ebay.com/itm/Fender-Stratocaster-HSS-Tobacco-Sunburst-W-Hard-Case-/333010106076", "ListingType": "FixedPriceItem", "Location": "Stafford, Virginia", "PaymentMethods": ["PayPal"], "GalleryURL": "https://thumbs1.ebaystatic.com/pict/3330101060768080_1.jpg", "PictureURL": ["https://i.ebayimg.com/00/s/MTYwMFgxMjAw/z/zt0AAOSwa55cOQZZ/$_57.JPG?set_id=8800005007", "https://i.ebayimg.com/00/s/MTYwMFgxMjAw/z/UykAAOSwN11cOQZb/$_57.JPG?set_id=8800005007", "https://i.ebayimg.com/00/s/MTYwMFgxMjAw/z/wtEAAOSwXc9cOQZf/$_57.JPG?set_id=8800005007", "https://i.ebayimg.com/00/s/MTYwMFgxMjAw/z/kK0AAOSwoRpcOQZi/$_57.JPG?set_id=8800005007", "https://i.ebayimg.com/00/s/MTYwMFgxMjAw/z/9QMAAOSw~2VcOQZk/$_57.JPG?set_id=8800005007", "https://i.ebayimg.com/00/s/MTIwMFgxNjAw/z/2MoAAOSwkDtcOQZp/$_57.JPG?set_id=8800005007"], "PostalCode": "22554", "PrimaryCategoryID": "33034", "PrimaryCategoryName": "Musical Instruments & Gear:Guitars & Basses:Electric Guitars", "Quantity": 1, "Seller": {"UserID": "bangmusic", "FeedbackRatingStar": "Turquoise", "FeedbackScore": 316, "PositiveFeedbackPercent": 100.0}, "BidCount": 0, "ConvertedCurrentPrice": {"Value": 400.0, "CurrencyID": "USD"}, "CurrentPrice": {"Value": 400.0, "CurrencyID": "USD"}, "HighBidder": {"UserID": "m***s", "FeedbackPrivate": false, "FeedbackRatingStar": "Purple", "FeedbackScore": 588}, "ListingStatus": "Completed", "QuantitySold": 1, "ShipToLocations": ["US"], "Site": "US", "TimeLeft": "PT0S", "Title": "Fender Stratocaster HSS Tobacco Sunburst W/ Hard Case", "ItemSpecifics": {"NameValueList": [{"Name": "Brand", "Value": ["Fender"]}, {"Name": "Model", "Value": ["Stratocaster HSS"]}, {"Name": "MPN", "Value": ["Does Not Apply"]}, {"Name": "Body Color", "Value": ["tobacco sunburst"]}, {"Name": "String Configuration", "Value": ["6 String"]}, {"Name": "Body Material", "Value": ["Alder"]}, {"Name": "Size", "Value": ["22 inch"]}, {"Name": "Right-/ Left-Handed", "Value": ["Right-Handed"]}]}, "HitCount": 48, "PrimaryCategoryIDPath": "619:3858:33034", "Storefront": {"StoreURL": "https://stores.ebay.com/id=14652306", "StoreName": "BANGMUSIC"}, "Country": "US", "ReturnPolicy": {"Refund": "Money Back", "ReturnsWithin": "14 Days", "ReturnsAccepted": "Returns Accepted", "ShippingCostPaidBy": "Buyer", "InternationalReturnsAccepted": "ReturnsNotAccepted"}, "AutoPay": true, "PaymentAllowedSite": [], "IntegratedMerchantCreditCardEnabled": false, "HandlingTime": 1, "ConditionID": 3000, "ConditionDisplayName": "Used", "GlobalShipping": false, "ConditionDescription": "This item is in great condition, there are no visible scratches or marks and it sounds fantastic.", "QuantitySoldByPickupInStore": 0, "NewBestOffer": false}