{"itemId": ["153305180663"], "title": ["Suhr Classic T Contoured Body 2015 Bengal Burst, Burl maple top"], "globalId": ["EBAY-US"], "primaryCategory": [{"categoryId": ["33034"], "categoryName": ["Electric Guitars"]}], "galleryURL": ["http://thumbs4.ebaystatic.com/m/muLPL4pSlG0ER04Ew4taiKg/140.jpg"], "viewItemURL": ["http://www.ebay.com/itm/Suhr-Classic-T-Contoured-Body-2015-Bengal-Burst-Burl-maple-top-/153305180663"], "paymentMethod": ["PayPal"], "autoPay": ["false"], "postalCode": ["11235"], "location": ["Brooklyn,NY,USA"], "country": ["US"], "shippingInfo": [{"shippingServiceCost": [{"@currencyId": "USD", "__value__": "90.0"}], "shippingType": ["Flat"], "shipToLocations": ["Worldwide"], "expeditedShipping": ["false"], "oneDayShippingAvailable": ["false"], "handlingTime": ["3"]}], "sellingStatus": [{"currentPrice": [{"@currencyId": "USD", "__value__": "2599.0"}], "convertedCurrentPrice": [{"@currencyId": "USD", "__value__": "2599.0"}], "sellingState": ["EndedWithSales"]}], "listingInfo": [{"bestOfferEnabled": ["true"], "buyItNowAvailable": ["false"], "startTime": ["2018-12-15T22:41:36.000Z"], "endTime": ["2019-02-28T04:57:40.000Z"], "listingType": ["FixedPrice"], "gift": ["false"], "watchCount": ["35"]}], "returnsAccepted": ["false"], "condition": [{"conditionId": ["3000"], "conditionDisplayName": ["Used"]}], "isMultiVariationListing": ["false"], "pictureURLLarge": ["https://i.ebayimg.com/00/s/MTYwMFgxMDIz/z/BN0AAOSwxB5bxVdv/$_1.JPG"], "topRatedListing": ["false"]}