{"itemId": ["143109317306"], "title": ["Ibanez RG8FM Japan USED Free shipping ta678"], "globalId": ["EBAY-US"], "primaryCategory": [{"categoryId": ["33034"], "categoryName": ["Electric Guitars"]}], "galleryURL": ["http://thumbs3.ebaystatic.com/m/m-FlLTuVNpwH7nzTwCTH-xA/140.jpg"], "viewItemURL": ["http://www.ebay.com/itm/Ibanez-RG8FM-Japan-USED-Free-shipping-ta678-/143109317306"], "paymentMethod": ["PayPal"], "autoPay": ["true"], "postalCode": ["06605"], "location": ["Bridgeport,CT,USA"], "country": ["US"], "shippingInfo": [{"shippingServiceCost": [{"@currencyId": "USD", "__value__": "0.0"}], "shippingType": ["Free"], "shipToLocations": ["Worldwide"], "expeditedShipping": ["false"], "oneDayShippingAvailable": ["false"], "handlingTime": ["1"]}], "sellingStatus": [{"currentPrice": [{"@currencyId": "USD", "__value__": "490.0"}], "convertedCurrentPrice": [{"@currencyId": "USD", "__value__": "490.0"}], "sellingState": ["EndedWithSales"]}], "listingInfo": [{"bestOfferEnabled": ["true"], "buyItNowAvailable": ["false"], "startTime": ["2019-01-30T05:55:38.000Z"], "endTime": ["2019-02-24T08:25:52.000Z"], "listingType": ["StoreInventory"], "gift": ["false"], "watchCount": ["2"]}], "returnsAccepted": ["true"], "condition": [{"conditionId": ["3000"], "conditionDisplayName": ["Used"]}], "isMultiVariationListing": ["false"], "pictureURLLarge": ["https://i.ebayimg.com/00/s/MTYwMFg3Nzg=/z/hO0AAOSwL05cUTtF/$_1.JPG"], "topRatedListing": ["false"]}