{"itemId": ["273579930203"], "title": ["2014 Gibson Les Paul 120th Anniversary Seymour Duncan Upgrades Gig Bag"], "globalId": ["EBAY-US"], "primaryCategory": [{"categoryId": ["33034"], "categoryName": ["Electric Guitars"]}], "galleryURL": ["http://thumbs4.ebaystatic.com/m/mz53KyskRwSkp0IuvxwMDmg/140.jpg"], "viewItemURL": ["http://www.ebay.com/itm/2014-Gibson-Les-Paul-120th-Anniversary-Seymour-Duncan-Upgrades-Gig-Bag-/273579930203"], "paymentMethod": ["PayPal"], "autoPay": ["true"], "postalCode": ["77006"], "location": ["Houston,TX,USA"], "country": ["US"], "shippingInfo": [{"shippingServiceCost": [{"@currencyId": "USD", "__value__": "50.0"}], "shippingType": ["Flat"], "shipToLocations": ["Worldwide"], "expeditedShipping": ["false"], "oneDayShippingAvailable": ["false"], "handlingTime": ["3"]}], "sellingStatus": [{"currentPrice": [{"@currencyId": "USD", "__value__": "600.0"}], "convertedCurrentPrice": [{"@currencyId": "USD", "__value__": "600.0"}], "bidCount": ["3"], "sellingState": ["EndedWithSales"]}], "listingInfo": [{"bestOfferEnabled": ["false"], "buyItNowAvailable": ["false"], "startTime": ["2018-11-26T21:11:47.000Z"], "endTime": ["2018-12-01T21:11:47.000Z"], "listingType": ["Auction"], "gift": ["false"], "watchCount": ["1"]}], "returnsAccepted": ["false"], "galleryPlusPictureURL": ["http://galleryplus.ebayimg.com/ws/web/273579930203_1_0_1.jpg"], "condition": [{"conditionId": ["3000"], "conditionDisplayName": ["Used"]}], "isMultiVariationListing": ["false"], "pictureURLLarge": ["https://i.ebayimg.com/00/s/MTYwMFgxMjAw/z/8v0AAOSwWSlb-4Df/$_1.JPG"], "topRatedListing": ["false"]}