{"itemId": ["132863497820"], "title": ["Epiphone Ltd Ed Joe Bonamassa 1958 Amos Flying-V w/ Case - Needs Selector Switch"], "globalId": ["EBAY-US"], "primaryCategory": [{"categoryId": ["33034"], "categoryName": ["Electric Guitars"]}], "galleryURL": ["http://thumbs1.ebaystatic.com/m/mWIiXIpthdBM9ZrKUrU7Ebw/140.jpg"], "viewItemURL": ["http://www.ebay.com/itm/Epiphone-Ltd-Ed-Joe-Bonamassa-1958-Amos-Flying-V-w-Case-Needs-Selector-Switch-/132863497820"], "paymentMethod": ["PayPal"], "autoPay": ["false"], "postalCode": ["46818"], "location": ["Fort Wayne,IN,USA"], "country": ["US"], "shippingInfo": [{"shippingServiceCost": [{"@currencyId": "USD", "__value__": "0.0"}], "shippingType": ["Free"], "shipToLocations": ["Worldwide"], "expeditedShipping": ["false"], "oneDayShippingAvailable": ["false"], "handlingTime": ["1"]}], "sellingStatus": [{"currentPrice": [{"@currencyId": "USD", "__value__": "698.0"}], "convertedCurrentPrice": [{"@currencyId": "USD", "__value__": "698.0"}], "bidCount": ["4"], "sellingState": ["EndedWithSales"]}], "listingInfo": [{"bestOfferEnabled": ["false"], "buyItNowAvailable": ["false"], "startTime": ["2018-11-22T02:34:28.000Z"], "endTime": ["2018-11-29T02:34:28.000Z"], "listingType": ["Auction"], "gift": ["false"], "watchCount": ["20"]}], "returnsAccepted": ["true"], "condition": [{"conditionId": ["3000"], "conditionDisplayName": ["Used"]}], "isMultiVariationListing": ["false"], "pictureURLLarge": ["https://i.ebayimg.com/00/s/OTYxWDE2MDA=/z/7JoAAOSwNX1b9XLb/$_1.JPG"], "topRatedListing": ["true"]}