{"itemId": ["283390482325"], "title": ["ESP LTD Viper 407 Seven String Satin Black Electric Guitar"], "globalId": ["EBAY-US"], "primaryCategory": [{"categoryId": ["33034"], "categoryName": ["Electric Guitars"]}], "galleryURL": ["http://thumbs2.ebaystatic.com/m/mRIUUD0Y7Xbs4Pt8UE8O1jQ/140.jpg"], "viewItemURL": ["http://www.ebay.com/itm/ESP-LTD-Viper-407-Seven-String-Satin-Black-Electric-Guitar-/283390482325"], "paymentMethod": ["PayPal"], "autoPay": ["false"], "postalCode": ["89011"], "location": ["Henderson,NV,USA"], "country": ["US"], "shippingInfo": [{"shippingServiceCost": [{"@currencyId": "USD", "__value__": "0.0"}], "shippingType": ["FreePickup"], "shipToLocations": ["Worldwide"], "expeditedShipping": ["true"], "oneDayShippingAvailable": ["false"], "handlingTime": ["3"]}], "sellingStatus": [{"currentPrice": [{"@currencyId": "USD", "__value__": "275.0"}], "convertedCurrentPrice": [{"@currencyId": "USD", "__value__": "275.0"}], "sellingState": ["EndedWithSales"]}], "listingInfo": [{"bestOfferEnabled": ["true"], "buyItNowAvailable": ["false"], "startTime": ["2019-02-22T18:08:17.000Z"], "endTime": ["2019-02-26T04:42:06.000Z"], "listingType": ["FixedPrice"], "gift": ["false"], "watchCount": ["12"]}], "returnsAccepted": ["false"], "condition": [{"conditionId": ["3000"], "conditionDisplayName": ["Used"]}], "isMultiVariationListing": ["false"], "pictureURLLarge": ["https://i.ebayimg.com/00/s/MTYwMFgxMjAw/z/3NQAAOSwKqNcb5D3/$_1.JPG"], "topRatedListing": ["false"]}