{"itemId": ["372556354874"], "title": ["Fender SQUIER STRAT Guitar Affinity Series- Tobacco Sunburst"], "globalId": ["EBAY-US"], "primaryCategory": [{"categoryId": ["33034"], "categoryName": ["Electric Guitars"]}], "galleryURL": ["http://thumbs3.ebaystatic.com/m/m8-N6N0YXZA3UKHtXtfat1w/140.jpg"], "viewItemURL": ["http://www.ebay.com/itm/Fender-SQUIER-STRAT-Guitar-Affinity-Series-Tobacco-Sunburst-/372556354874"], "paymentMethod": ["PayPal"], "autoPay": ["true"], "postalCode": ["55448"], "location": ["Minneapolis,MN,USA"], "country": ["US"], "shippingInfo": [{"shippingServiceCost": [{"@currencyId": "USD", "__value__": "0.0"}], "shippingType": ["Free"], "shipToLocations": ["Worldwide"], "expeditedShipping": ["false"], "oneDayShippingAvailable": ["false"], "handlingTime": ["1"]}], "sellingStatus": [{"currentPrice": [{"@currencyId": "USD", "__value__": "120.3"}], "convertedCurrentPrice": [{"@currencyId": "USD", "__value__": "120.3"}], "sellingState": ["EndedWithSales"]}], "listingInfo": [{"bestOfferEnabled": ["false"], "buyItNowAvailable": ["false"], "startTime": ["2019-01-03T16:03:34.000Z"], "endTime": ["2019-01-18T15:40:56.000Z"], "listingType": ["FixedPrice"], "gift": ["false"], "watchCount": ["6"]}], "returnsAccepted": ["true"], "condition": [{"conditionId": ["3000"], "conditionDisplayName": ["Used"]}], "isMultiVariationListing": ["false"], "pictureURLLarge": ["https://i.ebayimg.com/00/s/MTEwMFgxMTAw/z/6iwAAOSw~2VcLjJY/$_1.JPG"], "topRatedListing": ["true"]}