{"itemId": ["202495301985"], "title": ["MEMPHIS STRATOCASTER GUITAR PROJECT! BODY! HUMBUCKER PICKUPS! VINTAGE NECK!"], "globalId": ["EBAY-US"], "primaryCategory": [{"categoryId": ["33034"], "categoryName": ["Electric Guitars"]}], "galleryURL": ["http://thumbs2.ebaystatic.com/m/mVjGTrtOMsUbQaO6hl0BDGA/140.jpg"], "viewItemURL": ["http://www.ebay.com/itm/MEMPHIS-STRATOCASTER-GUITAR-PROJECT-BODY-HUMBUCKER-PICKUPS-VINTAGE-NECK-/202495301985"], "paymentMethod": ["PayPal"], "autoPay": ["false"], "postalCode": ["27525"], "location": ["Franklinton,NC,USA"], "country": ["US"], "shippingInfo": [{"shippingServiceCost": [{"@currencyId": "USD", "__value__": "18.0"}], "shippingType": ["Flat"], "shipToLocations": ["Worldwide"], "expeditedShipping": ["false"], "oneDayShippingAvailable": ["false"], "handlingTime": ["0"]}], "sellingStatus": [{"currentPrice": [{"@currencyId": "USD", "__value__": "114.5"}], "convertedCurrentPrice": [{"@currencyId": "USD", "__value__": "114.5"}], "bidCount": ["7"], "sellingState": ["EndedWithSales"]}], "listingInfo": [{"bestOfferEnabled": ["false"], "buyItNowAvailable": ["false"], "startTime": ["2018-11-08T01:00:01.000Z"], "endTime": ["2018-11-15T01:00:01.000Z"], "listingType": ["Auction"], "gift": ["false"], "watchCount": ["18"]}], "returnsAccepted": ["false"], "condition": [{"conditionId": ["3000"], "conditionDisplayName": ["Used"]}], "isMultiVariationListing": ["false"], "pictureURLLarge": ["https://i.ebayimg.com/00/s/MTYwMFgxMjAw/z/-BYAAOSw8-lb43Rt/$_1.JPG"], "topRatedListing": ["false"]}