{"BestOfferEnabled": false, "Description": "Here you get a Barron Mini Electric Guitar. Wood with black metallic paint. It also comes with carrying bag. It is in exceptional condition. It measures 29\u201d tall. Great mini guitar.", "ItemID": "253206986157", "EndTime": "2019-02-05T18:52:37.000Z", "StartTime": "2017-10-13T18:52:37.000Z", "ViewItemURLForNaturalSearch": "https://www.ebay.com/itm/Barron-Mini-Electric-Guitar-Matalic-Black-/253206986157", "ListingType": "FixedPriceItem", "Location": "Salem, New Jersey", "PaymentMethods": ["PayPal"], "GalleryURL": "https://thumbs2.ebaystatic.com/pict/2532069861578080_1.jpg", "PictureURL": ["https://i.ebayimg.com/00/s/NTAxWDE1NDQ=/z/~zcAAOSwNsRZ4Qb6/$_12.JPG?set_id=880000500F", "https://i.ebayimg.com/00/s/NTYxWDE2MDA=/z/U~QAAOSwEyhZ4QdB/$_12.JPG?set_id=880000500F", "https://i.ebayimg.com/00/s/ODE1WDE1OTE=/z/VZQAAOSwazJZ4QdC/$_12.JPG?set_id=880000500F", "https://i.ebayimg.com/00/s/MTAyOVgxNTA4/z/TkgAAOSwlepZ4Qb7/$_12.JPG?set_id=880000500F", "https://i.ebayimg.com/00/s/MTA1MFgxMjI5/z/i68AAOSwB-tZ4Qb7/$_12.JPG?set_id=880000500F", "https://i.ebayimg.com/00/s/MTQyN1g2NTE=/z/5NcAAOSw9XhZ4Qb8/$_12.JPG?set_id=880000500F", "https://i.ebayimg.com/00/s/MTYwMFgxMjAw/z/EykAAOSwovFZ4Qb~/$_12.JPG?set_id=880000500F", "https://i.ebayimg.com/00/s/MTQxOFg5OTc=/z/qegAAOSwowNZ4Qb~/$_12.JPG?set_id=880000500F", "https://i.ebayimg.com/00/s/OTQ5WDE0NDU=/z/w5MAAOSwTw5Z4Qb-/$_12.JPG?set_id=880000500F", "https://i.ebayimg.com/00/s/MTM4NVg3NTg=/z/Y34AAOSwFiJZ4Qb~/$_12.JPG?set_id=880000500F", "https://i.ebayimg.com/00/s/MTU3Nlg1MDA=/z/15MAAOSw~g1Z4QcA/$_12.JPG?set_id=880000500F"], "PostalCode": "08079", "PrimaryCategoryID": "33034", "PrimaryCategoryName": "Musical Instruments & Gear:Guitars & Basses:Electric Guitars", "Quantity": 1, "Seller": {"UserID": "wilvaugha-6", "FeedbackRatingStar": "Turquoise", "FeedbackScore": 277, "PositiveFeedbackPercent": 100.0, "TopRatedSeller": true}, "BidCount": 0, "ConvertedCurrentPrice": {"Value": 88.0, "CurrencyID": "USD"}, "CurrentPrice": {"Value": 88.0, "CurrencyID": "USD"}, "ListingStatus": "Active", "QuantitySold": 0, "ShipToLocations": ["US"], "Site": "US", "TimeLeft": "PT16H32M31S", "Title": "Barron Mini Electric Guitar In Matalic Black", "ItemSpecifics": {"NameValueList": [{"Name": "Body Color", "Value": ["Metalic black"]}, {"Name": "Brand", "Value": ["Barron"]}, {"Name": "Body Type", "Value": ["Mini cutout"]}, {"Name": "Model", "Value": ["Electric guitar"]}, {"Name": "String Configuration", "Value": ["6 String"]}, {"Name": "Dexterity", "Value": ["Right-Handed"]}, {"Name": "Body Material", "Value": ["Solid Wood"]}]}, "HitCount": 671, "PrimaryCategoryIDPath": "619:3858:33034", "Storefront": {"StoreURL": "https://stores.ebay.com/id=1647042567", "StoreName": "little shop in the middle"}, "Country": "US", "ReturnPolicy": {"ReturnsAccepted": "ReturnsNotAccepted"}, "AutoPay": false, "PaymentAllowedSite": [], "IntegratedMerchantCreditCardEnabled": false, "HandlingTime": 3, "ConditionID": 3000, "ConditionDisplayName": "Used", "GlobalShipping": false, "QuantitySoldByPickupInStore": 0, "NewBestOffer": false}