{"BestOfferEnabled": true, "Description": "SOONER STATE PAWN, LLC DEAN GUITARS ML XT WITH FLOYD ROSE AND DEAN HARDCASE BUNDLE Description: ELECTRIC GUITAR: DEAN GUITARS MODEL ML XT, 6 STRING, RIGHT HANDED, THERE ARE SEVERAL DENTS, DINGS AND SCRATCHES ON THIS PLAYER'S GUITAR. THERE ARE A COUPLE HAIRLINE CRACKS IN THE FINISH AT THE NECK JOINT. Details Additional Details for eCommerceDEAN GUITARS ML XT WITH FLOYD ROSE AND DEAN HARDCASE BUNDLE Musical Instrument Condition Rating85% - Good - Item in Good Working Order, but Has Some Visual Imperfections Instrument Appearance80% - Noticeable cosmetic scuffs, scratches, nicks that may reduce the items value. May have identifiable markings. Knobs - Tuners - Electronics - Input Jack85% - Guitar shows wear - All original - Scratches and chips maybe present - Controls show normal use and are in working condition - Discoloration maybe present. Musical Instrument CaseOriginal Manufacture Hard Case Included Number of Strings6 STRING Country of ManufactureOTHER COUNTRY Body StyleSOLID DexterityRight Handed Payment PayPal is the ONLY online payment method we accept at this time. Your PayPal account must be a Verified U.S. PayPal Account. We also recommend that you use a Confirmed Ship To Address. Shipping Your item will be shipped within 1 business day(s). After shipping your items will be delivered within 1-10 business days. Terms of Sale Tax applies in: OK About Us We carry a large variety of inventory. Whether you are shopping for new or used Firearms, a Diamond ring, or a gently used guitar, we have it! Our staff is always eager to answer any questions and help you with all of your needs! Things I Buy: gold, silver, firearms Bravo Store Systems Point-of-Sale Operating System Bravo Omni-Commerce solutions offers Brick & Mortar stores the only fully integrated eBay API that seamlessly & effortlessly combines the in-store Point-of-Sale to all eBay commerce selling activities. Click here & find out why eBay stated \"Bravo has best solved Brick & Mortars can sell on eBay\"", "ItemID": "223174140424", "EndTime": "2019-03-02T19:52:31.000Z", "StartTime": "2018-10-03T19:52:31.000Z", "ViewItemURLForNaturalSearch": "https://www.ebay.com/itm/DEAN-GUITARS-ML-XT-FLOYD-ROSE-AND-DEAN-HARDCASE-BUNDLE-SS2025602-/223174140424", "ListingType": "FixedPriceItem", "Location": "Oklahoma City, Oklahoma", "PaymentMethods": ["PayPal"], "GalleryURL": "https://thumbs1.ebaystatic.com/pict/2231741404248080_1.jpg", "PictureURL": ["https://i.ebayimg.com/00/s/NjcyWDUwNA==/z/ywYAAOSwZPdbtR3d/$_1.JPG?set_id=2", "https://i.ebayimg.com/00/s/NjcyWDUwNA==/z/qKkAAOSw1u9btR3e/$_1.JPG?set_id=2", "https://i.ebayimg.com/00/s/NjcyWDUwNA==/z/82IAAOSwSm9btR3g/$_1.JPG?set_id=2", "https://i.ebayimg.com/00/s/NjcyWDUwNA==/z/w0AAAOSwZhtbtR3j/$_1.JPG?set_id=2", "https://i.ebayimg.com/00/s/NjcyWDUwNA==/z/xVYAAOSwrHxbtR3n/$_1.JPG?set_id=2", "https://i.ebayimg.com/00/s/NjcyWDUwNA==/z/Qb4AAOSwlINbtR3q/$_1.JPG?set_id=2", "https://i.ebayimg.com/00/s/NjcyWDUwNA==/z/xMYAAOSwV-NbtR3u/$_1.JPG?set_id=2", "https://i.ebayimg.com/00/s/NjcyWDUwNA==/z/A7kAAOSwEJlbtR3v/$_1.JPG?set_id=2", "https://i.ebayimg.com/00/s/NjcyWDUwNA==/z/vawAAOSwfbhbtR3w/$_1.JPG?set_id=2", "https://i.ebayimg.com/00/s/NjcyWDUwNA==/z/ahQAAOSwg65btR31/$_1.JPG?set_id=2", "https://i.ebayimg.com/00/s/NjcyWDUwNA==/z/9NIAAOSwOYRbtR32/$_1.JPG?set_id=2", "https://i.ebayimg.com/00/s/NjcyWDUwNA==/z/DXYAAOSw1IVbtR37/$_1.JPG?set_id=2"], "PostalCode": "73107", "PrimaryCategoryID": "33034", "PrimaryCategoryName": "Musical Instruments & Gear:Guitars & Basses:Electric Guitars", "Quantity": 1, "Seller": {"UserID": "ssp2006", "FeedbackRatingStar": "Red", "FeedbackScore": 4924, "PositiveFeedbackPercent": 99.7, "TopRatedSeller": true}, "BidCount": 0, "ConvertedCurrentPrice": {"Value": 299.99, "CurrencyID": "USD"}, "CurrentPrice": {"Value": 299.99, "CurrencyID": "USD"}, "ListingStatus": "Active", "QuantitySold": 0, "ShipToLocations": ["US"], "Site": "US", "TimeLeft": "P25DT22H45M10S", "Title": "DEAN GUITARS ML XT WITH FLOYD ROSE AND DEAN HARDCASE BUNDLE (SS2025602)", "ItemSpecifics": {"NameValueList": [{"Name": "Brand", "Value": ["Dean Guitars"]}, {"Name": "Model", "Value": ["ML XT"]}]}, "HitCount": 1460, "PrimaryCategoryIDPath": "619:3858:33034", "Storefront": {"StoreURL": "https://stores.ebay.com/id=1120664815", "StoreName": "ssp2006"}, "Country": "US", "ReturnPolicy": {"Refund": "Money Back", "ReturnsWithin": "30 Days", "ReturnsAccepted": "Returns Accepted", "ShippingCostPaidBy": "Buyer"}, "AutoPay": false, "PaymentAllowedSite": [], "IntegratedMerchantCreditCardEnabled": false, "HandlingTime": 1, "ConditionID": 3000, "ConditionDisplayName": "Used", "GlobalShipping": false, "QuantitySoldByPickupInStore": 0, "NewBestOffer": false}