{"BestOfferEnabled": true, "Description": "Very nice Fender FSR Strat. Daphne Blue. Has a small ding on bottom of guitar. Other than that its perfect.", "ItemID": "192744533437", "EndTime": "2018-12-08T23:15:36.000Z", "StartTime": "2018-12-01T23:15:36.000Z", "ViewItemURLForNaturalSearch": "https://www.ebay.com/itm/Fender-Stratocaster-American-Standard-Electric-Guitar-/192744533437", "ListingType": "Chinese", "Location": "Conway, Arkansas", "PaymentMethods": ["PayPal"], "GalleryURL": "https://thumbs2.ebaystatic.com/pict/1927445334378080_1.jpg", "PictureURL": ["https://i.ebayimg.com/00/s/MTYwMFgxMjAw/z/FO8AAOSw1tJcAxRW/$_32.JPG?set_id=880000500F", "https://i.ebayimg.com/00/s/MTYwMFgxMjAw/z/iSkAAOSwXAxcAxRP/$_32.JPG?set_id=880000500F", "https://i.ebayimg.com/00/s/MTYwMFgxMjAw/z/7yEAAOSwHjtcAxRV/$_32.JPG?set_id=880000500F"], "PostalCode": "72034", "PrimaryCategoryID": "33034", "PrimaryCategoryName": "Musical Instruments & Gear:Guitars & Basses:Electric Guitars", "Quantity": 1, "Seller": {"UserID": "lisbel-62", "FeedbackRatingStar": "Turquoise", "FeedbackScore": 130, "PositiveFeedbackPercent": 100.0}, "BidCount": 1, "ConvertedCurrentPrice": {"Value": 800.0, "CurrencyID": "USD"}, "CurrentPrice": {"Value": 800.0, "CurrencyID": "USD"}, "HighBidder": {"UserID": "0***p", "FeedbackPrivate": false, "FeedbackRatingStar": "Yellow", "FeedbackScore": 31}, "ListingStatus": "Completed", "QuantitySold": 1, "ShipToLocations": ["US"], "Site": "US", "TimeLeft": "PT0S", "Title": "Fender Stratocaster American Standard Electric Guitar", "ItemSpecifics": {"NameValueList": [{"Name": "String Configuration", "Value": ["6 String"]}, {"Name": "Brand", "Value": ["Fender"]}, {"Name": "Model", "Value": ["Stratocaster American Standard"]}, {"Name": "Body Color", "Value": ["White"]}, {"Name": "Body Type", "Value": ["Solid"]}, {"Name": "MPN", "Value": ["113302705"]}]}, "HitCount": 248, "PrimaryCategoryIDPath": "619:3858:33034", "Country": "US", "ReturnPolicy": {"ReturnsAccepted": "ReturnsNotAccepted"}, "MinimumToBid": {"Value": 810.0, "CurrencyID": "USD"}, "ProductID": {"Value": "219517709", "Type": "Reference"}, "AutoPay": false, "PaymentAllowedSite": [], "IntegratedMerchantCreditCardEnabled": false, "HandlingTime": 2, "ConditionID": 3000, "ConditionDisplayName": "Used", "GlobalShipping": false, "QuantitySoldByPickupInStore": 0, "NewBestOffer": false}