{"BestOfferEnabled": false, "Description": "Great value for a beginner! Bundle includes everything you need to get started: Black Epiphone ES335 ProFender Champion 20 amplifierCordHard caseStandVox headphone amplifer- plug in with your headphones for private playing", "ItemID": "223320105378", "EndTime": "2019-01-10T22:18:05.000Z", "StartTime": "2019-01-10T22:13:48.000Z", "ViewItemURLForNaturalSearch": "https://www.ebay.com/itm/Guitar-Bundle-Black-Epiphone-ES-335-Pro-Case-Fender-Champion-20-Amp-More-/223320105378", "ListingType": "Chinese", "Location": "Cary, Illinois", "PaymentMethods": ["PayPal"], "GalleryURL": "https://thumbs3.ebaystatic.com/pict/2233201053788080_1.jpg", "PictureURL": ["https://i.ebayimg.com/00/s/MTQxOVgxNjAw/z/sDIAAOSw~KNcKO2O/$_57.JPG?set_id=8800005007", "https://i.ebayimg.com/00/s/MTYwMFg3NjI=/z/cx0AAOSwZ2tcKO2G/$_57.JPG?set_id=8800005007", "https://i.ebayimg.com/00/s/MTYwMFg3NjI=/z/vNMAAOSwa3FcKO2U/$_57.JPG?set_id=8800005007", "https://i.ebayimg.com/00/s/MTYwMFg3MDE=/z/joEAAOSwcnZcKOo6/$_57.JPG?set_id=8800005007", "https://i.ebayimg.com/00/s/NzYyWDE2MDA=/z/e-8AAOSwTEZcKOoz/$_57.JPG?set_id=8800005007", "https://i.ebayimg.com/00/s/MTYwMFg3NjI=/z/vOQAAOSwi3xcKO2l/$_57.JPG?set_id=8800005007", "https://i.ebayimg.com/00/s/MTYwMFg3NjI=/z/yUsAAOSwFx5cKO2s/$_57.JPG?set_id=8800005007", "https://i.ebayimg.com/00/s/NzQzWDEwMDE=/z/h7EAAOSwZ4RcKO25/$_57.JPG?set_id=8800005007", "https://i.ebayimg.com/00/s/MTU5OVgxMTEz/z/nUwAAOSwt~1cKOpG/$_57.JPG?set_id=8800005007", "https://i.ebayimg.com/00/s/MTYwMFgxMzEy/z/RYEAAOSwiT1cKOpK/$_57.JPG?set_id=8800005007", "https://i.ebayimg.com/00/s/NzYyWDE2MDA=/z/aAcAAOSwAFFcKOpM/$_57.JPG?set_id=8800005007"], "PostalCode": "60013", "PrimaryCategoryID": "33034", "PrimaryCategoryName": "Musical Instruments & Gear:Guitars & Basses:Electric Guitars", "Quantity": 1, "Seller": {"UserID": "twentyonecounter", "FeedbackRatingStar": "Yellow", "FeedbackScore": 19, "PositiveFeedbackPercent": 100.0}, "BidCount": 1, "ConvertedCurrentPrice": {"Value": 459.0, "CurrencyID": "USD"}, "CurrentPrice": {"Value": 459.0, "CurrencyID": "USD"}, "HighBidder": {"UserID": "4***m", "FeedbackPrivate": false, "FeedbackRatingStar": "None", "FeedbackScore": 7}, "ListingStatus": "Completed", "QuantitySold": 1, "ShipToLocations": ["US"], "Site": "US", "TimeLeft": "PT0S", "Title": "Guitar Bundle- Black Epiphone ES-335 Pro, Case, Fender Champion 20 Amp +More  ", "ItemSpecifics": {"NameValueList": [{"Name": "Brand", "Value": ["Epiphone"]}, {"Name": "Model Year", "Value": ["2016"]}, {"Name": "Modified Item", "Value": ["No"]}, {"Name": "Model", "Value": ["ES-335 Pro LE"]}, {"Name": "Right-/ Left-Handed", "Value": ["Right-Handed"]}, {"Name": "Bundle Description", "Value": ["Guitar, hard case, Fender Champion 20 amp, cord, stand, Vox Headphone Amplifier."]}, {"Name": "Country/Region of Manufacture", "Value": ["China"]}, {"Name": "Items Included", "Value": ["Hard Case, Fender Champion 20 Amp, Cord, Stand ++"]}, {"Name": "Nut Width", "Value": ["1 11/16\""]}, {"Name": "Body Color", "Value": ["Black"]}, {"Name": "Features", "Value": ["Mini-Block Inlays", "Rosewood Fretboard", "Split-Coil Humbuckers", "Limited Edition", "Tune-O-Matic Style Bridge", "Cream-Bound Neck/Body", "Wilkinson Vintage-Style Tuners (Jade)"]}, {"Name": "Product Line", "Value": ["Epiphone Limited Edition"]}, {"Name": "Custom Bundle", "Value": ["Yes"]}, {"Name": "String Configuration", "Value": ["6 String"]}, {"Name": "Body Type", "Value": ["Semi-Hollow"]}, {"Name": "Size", "Value": ["24.75\" Scale"]}]}, "HitCount": 1, "Subtitle": "Almost new, barely used equipment.  Great value.", "PrimaryCategoryIDPath": "619:3858:33034", "Country": "US", "ReturnPolicy": {"ReturnsAccepted": "ReturnsNotAccepted", "InternationalReturnsAccepted": "ReturnsNotAccepted"}, "MinimumToBid": {"Value": 464.0, "CurrencyID": "USD"}, "AutoPay": true, "PaymentAllowedSite": [], "IntegratedMerchantCreditCardEnabled": false, "HandlingTime": 3, "ConditionID": 3000, "ConditionDisplayName": "Used", "ExcludeShipToLocation": ["Alaska/Hawaii", "US Protectorates", "APO/FPO", "PO Box"], "GlobalShipping": false, "ConditionDescription": "Barely used.  Two years old.", "QuantitySoldByPickupInStore": 0, "NewBestOffer": false}