{"BestOfferEnabled": true, "Description": "SC-90 Carvin Single Cutaway Custom Guitar. Condition is Used. Carvin locking tuners, Spersal. Abalone inlays. Fretboard radius is 14\u201d. AAAA Quilted maple color. Two classic series humbucker pickups. Tongue oiled neck. Rosewood fretboard. Only used for about one year, excellent condition. PayPal only. Please message me with any questions about this listing. Shipping UPS ground, calculated. NO RETURNS ON THIS ITEM", "ItemID": "303065940513", "EndTime": "2019-02-22T23:40:54.000Z", "StartTime": "2019-02-17T22:37:48.000Z", "ViewItemURLForNaturalSearch": "https://www.ebay.com/itm/SC-90-Carvin-Single-Cutaway-Custom-Guitar-/303065940513", "ListingType": "Chinese", "Location": "Rockledge, Florida", "PaymentMethods": ["PayPal"], "GalleryURL": "https://thumbs2.ebaystatic.com/pict/3030659405138080_1.jpg", "PictureURL": ["https://i.ebayimg.com/00/s/MTYwMFgxMjAw/z/VTUAAOSwAopcRPdF/$_12.JPG?set_id=880000500F", "https://i.ebayimg.com/00/s/MTIwMFgxNjAw/z/n04AAOSwi3xcRPIq/$_12.JPG?set_id=880000500F", "https://i.ebayimg.com/00/s/MTYwMFgxMjAw/z/~j8AAOSwx9lcRPIF/$_12.JPG?set_id=880000500F", "https://i.ebayimg.com/00/s/MTYwMFgxMjAw/z/KmYAAOSwx3FcRPIJ/$_12.JPG?set_id=880000500F", "https://i.ebayimg.com/00/s/MTYwMFgxMjAw/z/cDAAAOSwLnRcRPIM/$_12.JPG?set_id=880000500F", "https://i.ebayimg.com/00/s/MTYwMFgxMjAw/z/PZMAAOSw-GNcRPIQ/$_12.JPG?set_id=880000500F", "https://i.ebayimg.com/00/s/MTYwMFgxMjAw/z/DuoAAOSwozNcRPIV/$_12.JPG?set_id=880000500F", "https://i.ebayimg.com/00/s/MTMwMFg4NTI=/z/dLQAAOSwJLJcRPKM/$_12.JPG?set_id=880000500F", "https://i.ebayimg.com/00/s/MTYwMFgxMjAw/z/zsUAAOSw2~NcRPKO/$_12.JPG?set_id=880000500F", "https://i.ebayimg.com/00/s/MTYwMFgxMjAw/z/vIEAAOSwwqVcRPKQ/$_12.JPG?set_id=880000500F", "https://i.ebayimg.com/00/s/MTYwMFgxMjAw/z/KogAAOSw1T1cRPKl/$_12.JPG?set_id=880000500F", "https://i.ebayimg.com/00/s/MTYwMFgxMjAw/z/rqkAAOSwy3JcRPKp/$_12.JPG?set_id=880000500F"], "PostalCode": "32955", "PrimaryCategoryID": "33034", "PrimaryCategoryName": "Musical Instruments & Gear:Guitars & Basses:Electric Guitars", "Quantity": 1, "Seller": {"UserID": "vinandcrystalsell", "FeedbackRatingStar": "Turquoise", "FeedbackScore": 376, "PositiveFeedbackPercent": 100.0}, "BidCount": 1, "ConvertedCurrentPrice": {"Value": 800.0, "CurrencyID": "USD"}, "CurrentPrice": {"Value": 800.0, "CurrencyID": "USD"}, "HighBidder": {"UserID": "b***_", "FeedbackPrivate": false, "FeedbackRatingStar": "None", "FeedbackScore": 5}, "ListingStatus": "Completed", "QuantitySold": 1, "ShipToLocations": ["US"], "Site": "US", "TimeLeft": "PT0S", "Title": "SC-90 Carvin Single Cutaway Custom Guitar", "ItemSpecifics": {"NameValueList": [{"Name": "Body Material", "Value": ["Mahogany"]}, {"Name": "Product Line", "Value": ["Carvin"]}, {"Name": "Brand", "Value": ["Carvin"]}, {"Name": "String Configuration", "Value": ["6 String"]}, {"Name": "Model", "Value": ["Custom"]}, {"Name": "Modified Item", "Value": ["No"]}, {"Name": "Right-/ Left-Handed", "Value": ["Right-Handed"]}, {"Name": "Body Type", "Value": ["Solid"]}, {"Name": "Body Color", "Value": ["Beige"]}, {"Name": "Features", "Value": ["Cutaway"]}]}, "HitCount": 148, "PrimaryCategoryIDPath": "619:3858:33034", "Country": "US", "ReturnPolicy": {"ReturnsAccepted": "ReturnsNotAccepted"}, "MinimumToBid": {"Value": 810.0, "CurrencyID": "USD"}, "AutoPay": false, "PaymentAllowedSite": [], "IntegratedMerchantCreditCardEnabled": false, "HandlingTime": 2, "ConditionID": 3000, "ConditionDisplayName": "Used", "GlobalShipping": false, "QuantitySoldByPickupInStore": 0, "NewBestOffer": false}