{"itemId": ["183565368286"], "title": ["Kramer Striker ST400MMB electric guitar, Floyd Rose, modded/repainted EMG Select"], "globalId": ["EBAY-US"], "primaryCategory": [{"categoryId": ["33034"], "categoryName": ["Electric Guitars"]}], "galleryURL": ["http://thumbs3.ebaystatic.com/m/mN9HezkFgIn_BcRvKU7VqTQ/140.jpg"], "viewItemURL": ["http://www.ebay.com/itm/Kramer-Striker-ST400MMB-electric-guitar-Floyd-Rose-modded-repainted-EMG-Select-/183565368286"], "paymentMethod": ["PayPal"], "autoPay": ["false"], "postalCode": ["60191"], "location": ["Wood Dale,IL,USA"], "country": ["US"], "shippingInfo": [{"shippingServiceCost": [{"@currencyId": "USD", "__value__": "40.0"}], "shippingType": ["Flat"], "shipToLocations": ["Worldwide"], "expeditedShipping": ["false"], "oneDayShippingAvailable": ["false"], "handlingTime": ["5"]}], "sellingStatus": [{"currentPrice": [{"@currencyId": "USD", "__value__": "185.0"}], "convertedCurrentPrice": [{"@currencyId": "USD", "__value__": "185.0"}], "sellingState": ["Active"], "timeLeft": ["P26DT4H20M34S"]}], "listingInfo": [{"bestOfferEnabled": ["false"], "buyItNowAvailable": ["false"], "startTime": ["2018-12-03T01:29:42.000Z"], "endTime": ["2019-03-03T01:29:42.000Z"], "listingType": ["StoreInventory"], "gift": ["false"], "watchCount": ["21"]}], "returnsAccepted": ["false"], "condition": [{"conditionId": ["3000"], "conditionDisplayName": ["Used"]}], "isMultiVariationListing": ["false"], "topRatedListing": ["false"]}