{"itemId": ["173837573731"], "title": ["burberry mens sunglasses"], "globalId": ["EBAY-US"], "primaryCategory": [{"categoryId": ["79720"], "categoryName": ["Sunglasses"]}], "galleryURL": ["http://thumbs4.ebaystatic.com/m/mIIsqOV4Ni-MFeHj0aZWGWA/140.jpg"], "viewItemURL": ["http://www.ebay.com/itm/burberry-mens-sunglasses-/173837573731"], "paymentMethod": ["PayPal"], "autoPay": ["false"], "postalCode": ["33015"], "location": ["Hialeah,FL,USA"], "country": ["US"], "shippingInfo": [{"shippingServiceCost": [{"@currencyId": "USD", "__value__": "10.0"}], "shippingType": ["Flat"], "shipToLocations": ["Worldwide"], "expeditedShipping": ["false"], "oneDayShippingAvailable": ["false"], "handlingTime": ["2"]}], "sellingStatus": [{"currentPrice": [{"@currencyId": "USD", "__value__": "50.0"}], "convertedCurrentPrice": [{"@currencyId": "USD", "__value__": "50.0"}], "sellingState": ["EndedWithSales"]}], "listingInfo": [{"bestOfferEnabled": ["true"], "buyItNowAvailable": ["false"], "startTime": ["2019-03-15T17:16:37.000Z"], "endTime": ["2019-03-28T14:06:14.000Z"], "listingType": ["StoreInventory"], "gift": ["false"], "watchCount": ["3"]}], "returnsAccepted": ["false"], "condition": [{"conditionId": ["3000"], "conditionDisplayName": ["Pre-owned"]}], "isMultiVariationListing": ["false"], "pictureURLLarge": ["https://i.ebayimg.com/00/s/MTYwMFgxNjAw/z/iAsAAOSw-eJb5RoO/$_1.JPG"], "topRatedListing": ["false"]}